timer.py
Pmdr-1.0.7.data/data/pmdr/endalarm.mp3
Pmdr-1.0.7.data/data/pmdr/sbalarm.mp3
Pmdr-1.0.7.data/data/pmdr/stalarm.mp3
pmdr/__init__.py
pmdr/__main__.py
pmdr/application.py
pmdr/endalarm.mp3
pmdr/sbalarm.mp3
pmdr/stalarm.mp3
pmdr/timer.py
Pmdr-1.0.7.dist-info/LICENSE
Pmdr-1.0.7.dist-info/METADATA
Pmdr-1.0.7.dist-info/WHEEL
Pmdr-1.0.7.dist-info/entry_points.txt
Pmdr-1.0.7.dist-info/top_level.txt
Pmdr-1.0.7.dist-info/RECORD
